[
  {
    "message": "ぐにっ…ぬぷっ…。"
  },
  {
    "name": "真弓",
    "message": "あぐっ…ぅ…。"
  },
  {
    "name": "たかふみ",
    "message": "あの時のお前は信じられないくらいイヤらしかった。"
  },
  {
    "name": "真弓",
    "message": "ほ、本当ですか？"
  },
  {
    "name": "たかふみ",
    "message": "今までで一番、魅力的だった。"
  },
  {
    "name": "真弓",
    "message": "っ…ありがとう…ございます…。"
  },
  {
    "name": "たかふみ",
    "message": "お前が明夫の名前を呼んだ時に、俺は危うく果てそうになったぞ。"
  },
  {
    "name": "真弓",
    "message": "あ、あれはご主人様が喜んでくれると思って…。"
  },
  {
    "message": "ぐにっ…。"
  },
  {
    "name": "真弓",
    "message": "ひっ…ぃ…。"
  },
  {
    "name": "たかふみ",
    "message": "そう思ったならどうして続けようとしない？"
  },
  {
    "name": "真弓",
    "message": "あぐっ…あっ…す、凄い…本当に、凄い…ぃ…。"
  },
  {
    "name": "たかふみ",
    "message": "なんでもっと魅力的な女になろうとしない？"
  },
  {
    "name": "真弓",
    "message": "な、なんかご主人様を裏切ってる気がしてきて…。"
  },
  {
    "name": "たかふみ",
    "message": "お前は一人の女として俺と付き合うつもりか？"
  },
  {
    "message": "ぬぷっ…ぬぷっ…ぐにっ…。"
  },
  {
    "name": "真弓",
    "message": "あ…くぅ…っ…はあっ…はあっ…。"
  },
  {
    "name": "たかふみ",
    "message": "…答えろ。"
  },
  {
    "name": "真弓",
    "message": "っ、人妻として…ご主人様と…。"
  },
  {
    "name": "たかふみ",
    "message": "誰の人妻だ？"
  },
  {
    "name": "真弓",
    "message": "あ、明夫さん以外の…。"
  },
  {
    "name": "明夫",
    "message": "～っ！！"
  },
  {
    "name": "たかふみ",
    "message": "どうして明夫以外じゃないとダメなんだ？"
  },
  {
    "name": "真弓",
    "message": "っ、もっと幸せな家庭を築かないといけないから…。"
  },
  {
    "name": "たかふみ",
    "message": "それならやつに引導を渡さなくてどうする？"
  },
  {
    "name": "真弓",
    "message": "は、はい…。"
  },
  {
    "name": "たかふみ",
    "message": "お前自身がケジメをつけなくてどうする？"
  },
  {
    "message": "ぬぷっ…ずぶっ…ぬぷっ…。"
  },
  {
    "name": "真弓",
    "message": "あうっ…つけます…つけます…ぅ…。"
  },
  {
    "name": "たかふみ",
    "message": "約束するか？"
  },
  {
    "name": "真弓",
    "message": "や、約束する…あっ…あっ…い、いや…あんっ…はあっ…はあっ…。"
  },
  {
    "name": "たかふみ",
    "message": "じゃあ、お前がする事を明夫に伝えておけ。"
  },
  {
    "name": "真弓",
    "message": "あ、あなた…。"
  },
  {
    "name": "明夫",
    "message": "っ…。"
  },
  {
    "name": "真弓",
    "message": "あとで私とセックスして…。"
  },
  {
    "name": "明夫",
    "message": "う…っ…。"
  },
  {
    "name": "真弓",
    "message": "こ、今度は最後まで…ちゃんとするの…っ…あっ…あっ…き、気持ちいい…。"
  },
  {
    "message": "ぬぷっ…ずぐっ…ぬぷっ…ぬぷっ…。"
  },
  {
    "name": "真弓",
    "message": "ああ～～っ…おまんこが、気持ちいい…本当に凄いっ…はあっ…うぐっ…あぁ…ぅぅ…。"
  },
  {
    "name": "真弓",
    "message": "あぐっ…そ、そこ、いい…突いて…もっと、突いて…っ…ああっ…ひっ…ぃ…ぃ…。"
  },
  {
    "message": "ぐりっ…ぐりっ…ぐりっ…。"
  },
  {
    "name": "真弓",
    "message": "うっ…くっ…はぁ…っ…。"
  },
  {
    "message": "ぐりっ…ぐりっ…ぐりっ…。"
  },
  {
    "name": "真弓",
    "message": "あなた…。"
  },
  {
    "name": "明夫",
    "message": "っ…。"
  },
  {
    "name": "真弓",
    "message": "明夫…さん…。"
  },
  {
    "name": "明夫",
    "message": "う…ぐ…ぅ…。"
  },
  {
    "name": "真弓",
    "message": "私を、見て…お願い…。"
  },
  {
    "message": "ぐりっ、ぐりっ…ぐりっ…。"
  },
  {
    "name": "真弓",
    "message": "私、もうイっちゃう…だから、だから…。"
  },
  {
    "message": "びくっ…。"
  },
  {
    "name": "真弓",
    "message": "あぐ…っ…イ、イク…イク…ぅ…。"
  },
  {
    "message": "びっくん。"
  },
  {
    "name": "真弓",
    "message": "う～～～～～～～～～～～～～っ！！"
  },
  {
    "name": "明夫",
    "message": "っ…。"
  },
  {
    "message": "びくっ、びくっ、びくっ…。"
  },
  {
    "name": "真弓",
    "message": "き、気持ちいいっ…身体が溶けるぅ…。"
  },
  {
    "name": "真弓",
    "message": "あぐっ…ああっ…はあっ…はあっ…たぶん私、凄くいやらしい顔、してる…はあっ…はあっ…。"
  },
  {
    "name": "明夫",
    "message": "く…。"
  },
  {
    "name": "真弓",
    "message": "っ、城崎さんはこうやって…私を女にしてくれるの…はあっ…だからこれ以上、明夫さんとは、もう…はあっ…はあっ…。"
  },
  {
    "name": "明夫",
    "message": "う、うっ…ひっ…ぃ…。"
  },
  {
    "name": "真弓",
    "message": "…泣かないで。"
  },
  {
    "name": "明夫",
    "message": "うぐっ…ひっ…ひっ…。"
  },
  {
    "name": "真弓",
    "message": "…。"
  },
  {
    "name": "真弓",
    "message": "…ご主人様。"
  },
  {
    "name": "たかふみ",
    "message": "…何だ？"
  },
  {
    "name": "真弓",
    "message": "後ろの穴もおねだりしていいですか？"
  },
  {
    "name": "たかふみ",
    "message": "…めずらしいな。"
  },
  {
    "name": "真弓",
    "message": "最後だから明夫さんに全てを見て貰いたい。"
  },
  {
    "name": "たかふみ",
    "message": "いい心掛けだ。"
  },
  {
    "message": "ぬぷっ…ぐにっ…。"
  },
  {
    "name": "真弓",
    "message": "っ…。"
  },
  {
    "name": "たかふみ",
    "message": "今回もクリームはなしだぞ。"
  },
  {
    "name": "真弓",
    "message": "…平気です。"
  },
  {
    "message": "めりっ…ぐっ…ぐっ…ずっ…ぶ…。"
  },
  {
    "name": "真弓",
    "message": "く…っ…。"
  },
  {
    "message": "ずっ…ずっ…ずっ…ぷ…ぅ…。"
  },
  {
    "name": "真弓",
    "message": "っ…もっと…奥まで…。"
  },
  {
    "message": "ずぐっ…ずっ…ずぶ…ぅ…。"
  },
  {
    "name": "真弓",
    "message": "くっ…は…ぁ…凄い…ぃ…。"
  },
  {
    "message": "ずっ…ずっ…ぐっ…にぃ…。"
  },
  {
    "name": "真弓",
    "message": "あうっ…入ってくる…奥まで、入る…っ…。"
  },
  {
    "name": "たかふみ",
    "message": "くぅ…。"
  },
  {
    "message": "ずっ…めりっ…ずっ…ぷぅ…。"
  },
  {
    "name": "真弓",
    "message": "ああ～っ…こんなの、初めて…ご主人様ぁ…。"
  },
  {
    "name": "たかふみ",
    "message": "…望みを叶えて貰った気分はどうだ？"
  },
  {
    "name": "真弓",
    "message": "ま、真弓は幸せ者ですぅ…。"
  },
  {
    "name": "明夫",
    "message": "…っ…。"
  },
  {
    "name": "真弓",
    "message": "…明夫さん。"
  },
  {
    "name": "明夫",
    "message": "う～～っ！！"
  },
  {
    "name": "真弓",
    "message": "…無理に目を開けなくてもいい。"
  },
  {
    "name": "明夫",
    "message": "ぅ…く…っ…。"
  },
  {
    "name": "真弓",
    "message": "見なくても何をしてるかわかるはずだから。"
  },
  {
    "name": "明夫",
    "message": "うっ…うぅ…ひっ…。"
  },
  {
    "name": "真弓",
    "message": "これも城崎さんが教えてくれたの。最初は凄く痛かったけど、少しずつ慣れてきて…。"
  },
  {
    "message": "ずっ…。"
  },
  {
    "name": "真弓",
    "message": "っ…こっちの穴もおまんこと一緒なんだよ…。"
  },
  {
    "message": "ぬぷっ…。"
  },
  {
    "name": "真弓",
    "message": "うっ…あ、明夫さんには、信じられない…だろうけど…。"
  },
  {
    "message": "ぬぷっ…ぬぷっ…。"
  },
  {
    "name": "真弓",
    "message": "あ、あうっ…本当に…そう、なの…。"
  },
  {
    "message": "ずぷっ…ぬっ…ずぷっ…。"
  },
  {
    "name": "真弓",
    "message": "うっ…く…ぅ…。"
  },
  {
    "message": "ずっ…ぬぷっ…ぬちゃ…ぬぷっ…。"
  },
  {
    "name": "真弓",
    "message": "あぐっ…凄く奥まで、入ってくる…いつもと感じが、違う…ぅ…。"
  },
  {
    "name": "真弓",
    "message": "あ、ああっ…ほ、本当に違うの…あうっ…あぐっ…あっ…あっ…。"
  },
  {
    "name": "たかふみ",
    "message": "っ…。"
  },
  {
    "message": "感じが違うのはこっちも一緒だ。"
  },
  {
    "message": "挿入してる深さは普段の３割り増し。"
  },
  {
    "message": "限界に近いくらい真弓の腸壁は伸ばされている。"
  },
  {
    "message": "普通の女ならとんでもない事になりそう。"
  },
  {
    "message": "健気で従順な彼女ならではの行為と言っていい。"
  },
  {
    "message": "もちろん下卑た匂いなどまったくしてこない。"
  },
  {
    "message": "マンコと変わらず肉竿の表面を光らせるだけ。"
  },
  {
    "message": "いくら清潔好きな彼女とはいえ、呆れるくらい腸内も綺麗だった。"
  },
  {
    "name": "たかふみ",
    "message": "…洗浄してきたのか？"
  },
  {
    "name": "真弓",
    "message": "っ、ご主人様が、心身共に…あ、あうっ…清めろって…。"
  },
  {
    "name": "たかふみ",
    "message": "例の道具を使ったんだな。"
  },
  {
    "name": "真弓",
    "message": "は、はい…お借りしているエネマで…お尻の穴からぬるま湯を…あ、あっ…あうっ…はあっ…はあっ…。"
  },
  {
    "name": "たかふみ",
    "message": "…偉いぞ。"
  },
  {
    "name": "真弓",
    "message": "っ…ご褒美を…ください…。"
  },
  {
    "name": "たかふみ",
    "message": "何がいい？"
  },
  {
    "name": "真弓",
    "message": "もっと、強く…速く…突いて…。"
  },
  {
    "name": "たかふみ",
    "message": "…。"
  },
  {
    "message": "ずぐっ、ぬちゃ、ずぶっ、ぐにっ、ずぐっ…。"
  },
  {
    "name": "真弓",
    "message": "あぐっ…ぅぅ…気持ちいい…奥が凄く、感じますぅ…。"
  },
  {
    "name": "真弓",
    "message": "ひいっ…ぃ…こっちの穴でも…イッちゃいそう…あっ…いやぁ…うぐっ…あぐっ…ああぁ…ぁ…。"
  },
  {
    "message": "ぎゅうぅ…っ。"
  },
  {
    "name": "たかふみ",
    "message": "っ…生き物みたいだ。"
  },
  {
    "name": "真弓",
    "message": "あうっ…じ、自分でもわかる…くはぁ…ぐにぐに動いてる…あうっ…あっ…うっ…あっ…あっ…。"
  },
  {
    "message": "ぎゅっ、ぎゅっ、ぎゅっ…。"
  },
  {
    "name": "たかふみ",
    "message": "くぅ…。"
  },
  {
    "name": "真弓",
    "message": "あぐぅっ…イ、イク…お尻の穴でイッちゃう…こんなの恥ずかしい…っ…あっ…あうっ…あっ…あっ…。"
  },
  {
    "message": "ぎゅううう…っ…。"
  },
  {
    "name": "真弓",
    "message": "あ、あ～～～～～～～～っ！！"
  },
  {
    "message": "ぎゅっ、びくっ、ぎゅっ…びくっ…ん…。"
  },
  {
    "name": "真弓",
    "message": "あぐっ…あぐっ…本当に気持ちいい…っ…。"
  },
  {
    "name": "真弓",
    "message": "凄い、凄い…あはっ…イッてる…ご主人様、助けてっ…私、変になるっ…はあっ…はあっ…。"
  },
  {
    "message": "ぎゅっ、ぎゅっ…びく、びくっ…。"
  },
  {
    "name": "真弓",
    "message": "う、う～～～っ、ご主人様ぁっ…。"
  },
  {
    "message": "ぬぷぅっ…。"
  },
  {
    "name": "真弓",
    "message": "あっ…く…ぅ…。"
  },
  {
    "name": "たかふみ",
    "message": "今度はこっち、だ。"
  },
  {
    "message": "ずぶぅ…。"
  },
  {
    "name": "真弓",
    "message": "あ、あうっ…ま、また…？"
  },
  {
    "name": "たかふみ",
    "message": "…俺も果てそうなんだよ。"
  },
  {
    "name": "真弓",
    "message": "…え？"
  },
  {
    "name": "たかふみ",
    "message": "くくっ…。"
  },
  {
    "message": "ぬぷっ…。"
  },
  {
    "name": "真弓",
    "message": "じ、冗談ですよね？"
  },
  {
    "name": "たかふみ",
    "message": "さあ…。"
  },
  {
    "message": "ぬぷっ…ずぶっ…ぬぷっ…ずぶっ…。"
  },
  {
    "name": "真弓",
    "message": "っ、ちょっと待って下さい…あっ…い、いや…ご主人様、待って…。"
  },
  {
    "name": "たかふみ",
    "message": "旦那の前で出されるなんて最高だろ？"
  },
  {
    "message": "ぐりっ…。"
  },
  {
    "name": "真弓",
    "message": "ああ～～っ…だ、だめです…中はだめっ…やめて、やめて…。"
  },
  {
    "name": "たかふみ",
    "message": "明夫にお伺いを立ててみたらどうだ？"
  },
  {
    "name": "真弓",
    "message": "そ、そんなのダメに決まって…。"
  },
  {
    "name": "明夫",
    "message": "…。"
  },
  {
    "message": "明夫は完全に無視。"
  },
  {
    "message": "少しかぶりを振っただけ。"
  },
  {
    "message": "もう勝手にしろと言いたげだ。"
  },
  {
    "name": "真弓",
    "message": "あ、あなた…。"
  },
  {
    "message": "ぬぷっ…ぬぷっ…ぬぷっ…。"
  },
  {
    "name": "真弓",
    "message": "私、中で出されちゃう…赤ちゃんが、できちゃう…っ…。"
  },
  {
    "message": "ぬぷっ…ずっ…ぬぷっ…ぬぷっ…くちゅ…っ…。"
  },
  {
    "name": "真弓",
    "message": "っ…し、城崎さんの、すごく濃いの…量もいっぱい…だから中はだめ…出したらだめぇ…っ…。"
  },
  {
    "message": "ぐりっ…。"
  },
  {
    "name": "真弓",
    "message": "あっ…くっ…ぅ…い、いや…そこ、いや…。"
  },
  {
    "message": "ぐりっ、ぬぷっ、ぐりっ、ぬぷっ…。"
  },
  {
    "name": "真弓",
    "message": "あ、あぐっ…ま、またイク…っ…はあっ…でも中はだめっ…精液、欲しくない…あっ…イ、イク…イッちゃう…。"
  },
  {
    "name": "真弓",
    "message": "あはぁっ…き、気持ちいいっ…ご主人様ぁっ…はあっ…はあっ…凄いのくるっ…ぅ…。"
  },
  {
    "name": "たかふみ",
    "message": "一緒に果てようぜ。"
  },
  {
    "name": "真弓",
    "message": "い、いや～～～～～っ、お願いだからやめてっ…あぐっ…主人の前で中はいやぁ…っ…。"
  },
  {
    "name": "たかふみ",
    "message": "っ…。"
  },
  {
    "name": "真弓",
    "message": "あぐっ…だ、だめっ…許して…でもイク…私、イクぅ…気持ちいい…あっ…あっ…あっ…。"
  },
  {
    "message": "ぐりんっ。"
  },
  {
    "name": "真弓",
    "message": "～～～～～～～～～～～～～っ！！"
  },
  {
    "message": "ぎゅうううう、びっくん、びっくん…。"
  },
  {
    "name": "たかふみ",
    "message": "く…はっ…。"
  },
  {
    "message": "ずびゅっ！！"
  },
  {
    "name": "真弓",
    "message": "ひっ…。"
  },
  {
    "message": "びゅうっ、どびゅっ、どびゅっ、どびゅっ…。"
  }
]