[
  {
    "name": "真弓",
    "message": "あ…ぁ…おま…んこ…。"
  },
  {
    "name": "たかふみ",
    "message": "もっと大きな声で言えよ。"
  },
  {
    "name": "真弓",
    "message": "お、おまんこしてる…。"
  },
  {
    "name": "たかふみ",
    "message": "もっと。"
  },
  {
    "name": "真弓",
    "message": "おまんこしてるっ…私、おまんこ…してるぅ…っ。"
  },
  {
    "name": "たかふみ",
    "message": "それじゃ寝室にいる旦那様に聞こえないぜ。"
  },
  {
    "name": "真弓",
    "message": "っ…ごめんなさい。"
  },
  {
    "name": "たかふみ",
    "message": "何の為に扉を少し開けたんだ？"
  },
  {
    "name": "真弓",
    "message": "っ…っ…。"
  },
  {
    "name": "たかふみ",
    "message": "何なら中へ入ってやるか？"
  },
  {
    "name": "真弓",
    "message": "い、いや…主人が起きちゃう…それは絶対にだめっ…。"
  },
  {
    "name": "たかふみ",
    "message": "くくっ…。"
  },
  {
    "message": "スリル満点だな。"
  },
  {
    "message": "もちろん旦那様には例の眠剤を使用。"
  },
  {
    "message": "かと言って明夫の時みたいに、馬鹿みたいな量は仕込まない。"
  },
  {
    "message": "リスクを残したギリギリのさじ加減。"
  },
  {
    "message": "だからこそ俺には虐め甲斐が生まれ。"
  },
  {
    "message": "真弓だって虐められ甲斐が何倍にも膨れ上がる。"
  },
  {
    "message": "ぬぷっ…ぬちゅっ…ぬぷっ…ぬちゅっ…。"
  },
  {
    "name": "真弓",
    "message": "あっ…ぐっ…ぅ…はあっ…はあっ…はあっ…ご主人様…ぁ…っ。"
  },
  {
    "name": "真弓",
    "message": "気持ちいい…イッちゃう…はあっ…はあっ…んっ…う…はあっ…真弓、イッちゃ…う…っ。"
  },
  {
    "name": "たかふみ",
    "message": "…この淫乱妊婦め。"
  },
  {
    "name": "真弓",
    "message": "そ、そう…真弓は淫乱…です…。"
  },
  {
    "name": "たかふみ",
    "message": "どのくらい淫乱か説明してみろ。"
  },
  {
    "name": "真弓",
    "message": "おちんちん大好き…ご主人様の、おちんちん、大好きぃっ…ずっと入れていたいくらい、好きっ。"
  },
  {
    "name": "たかふみ",
    "message": "そう言いながら旦那様のも好きなんだろ？"
  },
  {
    "name": "真弓",
    "message": "っ…。"
  },
  {
    "message": "定番の意地悪な質問。"
  },
  {
    "message": "ここから先はお約束の展開だ。"
  },
  {
    "message": "真弓はまず躊躇するそぶり。"
  },
  {
    "message": "それからわざと俺の興奮を煽るよう、刺激的な言葉での返事を心掛ける。"
  },
  {
    "name": "真弓",
    "message": "っ、そんなの訊かれるまでもありません。"
  },
  {
    "name": "たかふみ",
    "message": "へえ…。"
  },
  {
    "message": "ずっ…。"
  },
  {
    "name": "真弓",
    "message": "ひ…。"
  },
  {
    "name": "たかふみ",
    "message": "どっちの意味で言ってる？"
  },
  {
    "name": "真弓",
    "message": "あ、あの人が一番に決まってます。"
  },
  {
    "name": "たかふみ",
    "message": "…俺よりいいんだな。"
  },
  {
    "name": "真弓",
    "message": "っ、だって最愛の旦那様ですもの。"
  },
  {
    "name": "たかふみ",
    "message": "そこまであのジジイに惚れてるのか？"
  },
  {
    "name": "真弓",
    "message": "す、好き…。"
  },
  {
    "name": "たかふみ",
    "message": "本当に？"
  },
  {
    "name": "真弓",
    "message": "っ、本当です…だから毎晩のように…主人とセックスして…。"
  },
  {
    "name": "たかふみ",
    "message": "っ…。"
  },
  {
    "message": "最近はこの言葉が俺にとってのツボ。"
  },
  {
    "message": "あのジジイと身体を交わらせる真弓の姿。"
  },
  {
    "message": "その肢体を頭に思い浮かべただけで、ペニスの硬度も二割増しになった。"
  },
  {
    "name": "たかふみ",
    "message": "…いつもどんな体位でしてるんだ？"
  },
  {
    "name": "真弓",
    "message": "っ…世界で一番いやらしい体位。"
  },
  {
    "name": "たかふみ",
    "message": "…その部分も詳しく説明してみな。"
  },
  {
    "message": "ずりっ…ずりっ…ぬぷっ…ぬぷ…ぅ…。"
  },
  {
    "name": "真弓",
    "message": "あぁ…す、凄い…ぁ…っ…ぁ…ぁ…奥に…くる…ぅ…。"
  },
  {
    "name": "たかふみ",
    "message": "…早く。"
  },
  {
    "name": "真弓",
    "message": "じ、自分から旦那様の上に跨って…自分からオマンコを開いて…。"
  },
  {
    "name": "真弓",
    "message": "自分でイヤらしく腰をくねらせて…わざとお尻の穴まで丸見えにして…はあっ…はあっ…だ、だめ…イッちゃいます…ご主人様ぁ…。"
  },
  {
    "name": "たかふみ",
    "message": "…許可してあげない。"
  },
  {
    "name": "真弓",
    "message": "っ…もう我慢できません。"
  },
  {
    "name": "たかふみ",
    "message": "お前が気持ち良くなっていいのは、大好きな旦那様のペニスだけだろ？"
  },
  {
    "name": "真弓",
    "message": "ご主人様がそうおっしゃるなら…。"
  },
  {
    "message": "ずりっ…ぐりっ…。"
  },
  {
    "name": "真弓",
    "message": "ひぃっ…ぃ…真弓は、真弓は…あうっ…が、我慢しない…と…。"
  },
  {
    "name": "たかふみ",
    "message": "…いい心掛けだ。"
  },
  {
    "message": "ずりっ…ぐりっ…ぬぷっ…ぬぷっ…ぬぷっ…。"
  },
  {
    "name": "真弓",
    "message": "あっ…はあっ…ひぃ…っ…はあっ…はあっ…。"
  },
  {
    "message": "ずりっ…ずりっ…くりっ…ずりっ…ずりっ…。"
  },
  {
    "name": "真弓",
    "message": "ああぁ…い、いやぁ…深いぃ…っ…そんなに虐めないで…はあっ…はあっ…真弓のオマンコ、虐めないでっ…。"
  },
  {
    "name": "真弓",
    "message": "っ、だめ…やっぱりイッちゃう…ご主人様の大きいから、やっぱりイッちゃう…どうしよう、どうしよう…っ…。"
  },
  {
    "name": "たかふみ",
    "message": "好きにすりゃいい。"
  },
  {
    "name": "真弓",
    "message": "か、勝手にイッたらご主人様から罰が…。"
  },
  {
    "name": "たかふみ",
    "message": "ああ、寝てる旦那様を起こして、目の前でアンタを犯してやるさ。"
  },
  {
    "name": "真弓",
    "message": "っ、だめっ…それだけは許してっ…あうっ…はあっ…はあっ…私、奥さんでいられない…あの人と離婚する事に…なる…ぅ。"
  },
  {
    "name": "たかふみ",
    "message": "そう思うなら我慢するしかねぇな。"
  },
  {
    "name": "真弓",
    "message": "で、でも我慢し続けると…。"
  },
  {
    "name": "たかふみ",
    "message": "…わかってるさ。"
  },
  {
    "message": "ずぶっ…ぬちゃっ…ずぶっ…ずぶっ…ぐりっ…。"
  },
  {
    "name": "真弓",
    "message": "ひぃぃっ…気持ち…いいっ…。"
  },
  {
    "name": "たかふみ",
    "message": "お前は快感を溜め込んだぶんだけ、凄い絶頂を迎えちゃう女だから。"
  },
  {
    "name": "真弓",
    "message": "はあっ…はあっ…失神するくらい気持ち良くなって…前もそうだった…ご主人様のおちんちんだと…真弓は…。"
  },
  {
    "name": "たかふみ",
    "message": "…旦那様が目覚めるくらいの、嬌声を上げちゃったりして。"
  },
  {
    "message": "ずぶっ…ぬぷっ…ずぶっ…ずぐっ…ずぶっ…。"
  },
  {
    "name": "真弓",
    "message": "ああっ…あっ…だからご主人様…あうっ…はあっ…はあっ…お願いですぅ…そうなる前に、果てる許可を…イク許可を…早く真弓に…っ。"
  },
  {
    "name": "たかふみ",
    "message": "そんなに離婚するのがイヤなのか？"
  },
  {
    "name": "真弓",
    "message": "い、いや…いや…ぁ…。"
  },
  {
    "name": "たかふみ",
    "message": "…なら仕方ねぇや。"
  }
]