[
  {
    "message": "……二日後……"
  },
  {
    "message": "平日の午後。"
  },
  {
    "message": "嬉しくもない定休日。"
  },
  {
    "message": "今日は特にクソ暑い。"
  },
  {
    "message": "俺の部屋はサウナか？"
  },
  {
    "message": "ボロいエアコンは店のババア以上に役立たず。"
  },
  {
    "message": "しかしそれにもめげず、俺はオナニーの最中だ。"
  },
  {
    "message": "レンタルしてきたアダルトビデオ。"
  },
  {
    "message": "もちろんジャンルは俺好みの強姦モノ。"
  },
  {
    "message": "しかしこれが最低だった。"
  },
  {
    "message": "臨場感を醸す演出なのか、画面が縦横無尽に揺れる。"
  },
  {
    "message": "アホか。"
  },
  {
    "message": "５分としないうち酔ってきた。"
  },
  {
    "message": "続いて結合部分の大アップ。"
  },
  {
    "message": "画面一杯モザイクだらけ。"
  },
  {
    "message": "もう何がなんだかわからない。"
  },
  {
    "message": "おまけに延々とそのシーンが続く。"
  },
  {
    "message": "嫌がらせか？"
  },
  {
    "message": "ここは日本なんだよ。"
  },
  {
    "message": "俺はテレビのスイッチを切る。"
  },
  {
    "message": "ビデオは回ったまま。"
  },
  {
    "message": "もはやテープを引き抜いて、返しに行く気も起こらない。"
  },
  {
    "message": "これなら真弓のマンコ写真を見て、オナニーをしたほうがマシだ。"
  },
  {
    "name": "たかふみ",
    "message": "…。"
  },
  {
    "message": "そう思って携帯に手を伸ばした時。"
  },
  {
    "message": "あたかも待っていたように着信音が鳴った。"
  },
  {
    "name": "たかふみ",
    "message": "…もしもし。"
  },
  {
    "message": "偶然にも相手は真弓。"
  },
  {
    "message": "やはり俺達には何か縁がある。"
  },
  {
    "message": "話をするのはあれ（レイプ）以来だ。"
  },
  {
    "message": "心なしか必死な真弓の声。"
  },
  {
    "message": "訊きたい事があるの一点張り。"
  },
  {
    "message": "とにかく一方的に喋ってくる。"
  },
  {
    "message": "退屈だ。"
  },
  {
    "message": "俺は床に放置された郵便物を拾い上げた。"
  },
  {
    "message": "借金の督促状。"
  },
  {
    "message": "ご利用は計画的に、だって？"
  },
  {
    "message": "計画的に金を使える人間は、借金などしない。"
  },
  {
    "message": "…。"
  },
  {
    "name": "たかふみ",
    "message": "…今日は暑いから嫌だね。セミもミンミン煩ぇし。"
  },
  {
    "message": "どうやら真弓は俺を公園に呼び出したいらしい。"
  },
  {
    "message": "このまま電話で訊けと言っても納得しない。"
  },
  {
    "message": "会ったらお小遣いでもくれるのか？"
  },
  {
    "name": "たかふみ",
    "message": "…わかったよ。"
  },
  {
    "message": "なんかもう面倒臭い。"
  },
  {
    "message": "耳と携帯の隙間も汗でベタベタしてくる。"
  },
  {
    "message": "返事をした俺はブチッと電話を切った。"
  },
  {
    "message": "俺を呼び出すなんていい根性をしてるな。"
  },
  {
    "message": "これでくだらない話だったら、首まで砂場の中に埋めてやる。"
  },
  {
    "message": "…。"
  },
  {
    "message": "……。"
  },
  {
    "message": "………。"
  },
  {
    "name": "真弓",
    "message": "…。"
  },
  {
    "name": "たかふみ",
    "message": "やあ、奥さん。"
  },
  {
    "name": "真弓",
    "message": "よくまともに私の顔を見られるわね。"
  },
  {
    "name": "たかふみ",
    "message": "会っていきなり恨み節か？"
  },
  {
    "name": "真弓",
    "message": "…。"
  },
  {
    "message": "ま、それはお互い様でしょ"
  },
  {
    "message": "言われてみれば確かにそうだな"
  },
  {
    "name": "たかふみ",
    "message": "ま、それはお互い様でしょ。"
  },
  {
    "name": "真弓",
    "message": "っ…。"
  },
  {
    "name": "たかふみ",
    "message": "言われてみれば確かにそうだな。"
  },
  {
    "name": "真弓",
    "message": "…あんたにも罪悪感ってものがあるわけね。"
  },
  {
    "name": "たかふみ",
    "message": "ううん、奥さんと結ばれた時の事を思い出すと、頬が赤くなるほど恥ずかしくなっちゃう…そういう意味。"
  },
  {
    "name": "真弓",
    "message": "…結ばれたなんて言い方、やめて。"
  },
  {
    "name": "たかふみ",
    "message": "解釈は人それぞれだろ？"
  },
  {
    "name": "真弓",
    "message": "っ…。"
  },
  {
    "name": "たかふみ",
    "message": "で、話って何よ。"
  },
  {
    "name": "真弓",
    "message": "訊きたい事があるの。"
  },
  {
    "name": "たかふみ",
    "message": "だからそれは電話で聞いてるって。"
  },
  {
    "name": "真弓",
    "message": "あんた、変な病気を持ってないでしょうね。"
  },
  {
    "name": "たかふみ",
    "message": "はあ？"
  },
  {
    "name": "真弓",
    "message": "答えて。"
  },
  {
    "name": "たかふみ",
    "message": "…この野郎。"
  },
  {
    "name": "真弓",
    "message": "こ、この野郎？"
  },
  {
    "name": "たかふみ",
    "message": "思いっきり電話で済む話じゃないか。脳が溶けそうなくらいクソ暑い時に、クソ暑い場所へ呼び出しやがって…。"
  },
  {
    "name": "真弓",
    "message": "それでなくてもあんたは嘘つきなんだから。顔を見ながらじゃないと信用できないのよっ。"
  },
  {
    "name": "たかふみ",
    "message": "…何だと？"
  },
  {
    "name": "真弓",
    "message": "私だって、あんたになんか会いたくもないわ。"
  },
  {
    "name": "たかふみ",
    "message": "ふん、亭主に変な病気を移したら大変ってか？"
  },
  {
    "name": "真弓",
    "message": "いいから答えて。"
  },
  {
    "name": "たかふみ",
    "message": "や・だ・ね。"
  },
  {
    "name": "真弓",
    "message": "…。"
  },
  {
    "name": "たかふみ",
    "message": "心配なら勝手に病院へ行けばいい。医者の前で股を開いて、診察してもらいな。"
  },
  {
    "name": "真弓",
    "message": "あの人に余計な心配をかけたくないから。"
  },
  {
    "name": "たかふみ",
    "message": "黙ってりゃわからないさ。"
  },
  {
    "name": "真弓",
    "message": "年末、誰がどこの病院に行ったか明細が来るでしょ？"
  },
  {
    "name": "たかふみ",
    "message": "妊娠ネタを理由にすりゃいい。"
  },
  {
    "name": "真弓",
    "message": "っ…。"
  },
  {
    "name": "たかふみ",
    "message": "結婚してるんだから問題ねぇだろ。"
  },
  {
    "name": "真弓",
    "message": "…無理よ。"
  },
  {
    "name": "たかふみ",
    "message": "どうして。"
  },
  {
    "name": "真弓",
    "message": "…主人に嘘はつきたくないの。"
  },
  {
    "name": "たかふみ",
    "message": "ちっ、ワガママな女だぜ。じゃあ、いっその事…。"
  },
  {
    "message": "離婚すりゃいい"
  },
  {
    "message": "俺が診てやるよ"
  },
  {
    "name": "たかふみ",
    "message": "離婚すりゃいい。"
  },
  {
    "name": "真弓",
    "message": "…ふざけないで。"
  },
  {
    "name": "たかふみ",
    "message": "けっこう真面目に答えたんだけどさ。"
  },
  {
    "name": "真弓",
    "message": "何の為に我慢したと思ってるのよっ。"
  },
  {
    "name": "たかふみ",
    "message": "我慢って、誰が？"
  },
  {
    "name": "真弓",
    "message": "ご、合意の元にあんな事をしたと思ってるわけ？"
  },
  {
    "name": "たかふみ",
    "message": "ロクに抵抗もしなかったじゃないか。"
  },
  {
    "name": "真弓",
    "message": "っ…。"
  },
  {
    "name": "たかふみ",
    "message": "俺が診てやるよ。"
  },
  {
    "name": "真弓",
    "message": "…ふざけないで。"
  },
  {
    "name": "たかふみ",
    "message": "女の身体は知り尽くしてるつもりだけど。"
  },
  {
    "name": "真弓",
    "message": "つまり、心のほうは全くわかってないって事ね。"
  },
  {
    "name": "たかふみ",
    "message": "…どういう意味だよ。"
  },
  {
    "name": "真弓",
    "message": "女心がわかってるなら、あんな酷い事はしない。"
  },
  {
    "name": "たかふみ",
    "message": "酷い事って？"
  },
  {
    "name": "真弓",
    "message": "一昨日あんたが私にした事よ。"
  },
  {
    "name": "たかふみ",
    "message": "なんだ、奥さんと俺が愛し合った事か。"
  },
  {
    "name": "真弓",
    "message": "…愛し合ったですって？"
  },
  {
    "name": "たかふみ",
    "message": "ああ。"
  },
  {
    "name": "真弓",
    "message": "っ、だからそういう言い方はやめてよ。"
  },
  {
    "name": "たかふみ",
    "message": "解釈は人それぞれって言っただろ？"
  },
  {
    "name": "真弓",
    "message": "わ、私が合意の元にしたと思ってるわけ？"
  },
  {
    "name": "たかふみ",
    "message": "だって、ロクに抵抗しなかったじゃないか。"
  },
  {
    "name": "真弓",
    "message": "っ…。"
  },
  {
    "name": "たかふみ",
    "message": "だろ？"
  },
  {
    "name": "真弓",
    "message": "…。"
  },
  {
    "name": "たかふみ",
    "message": "奥さんは自ら俺を受け入れたんだ。"
  },
  {
    "name": "真弓",
    "message": "…違う。"
  },
  {
    "name": "たかふみ",
    "message": "違わないさ。"
  },
  {
    "name": "真弓",
    "message": "…脅迫をされて、仕方なくだわ。"
  },
  {
    "name": "たかふみ",
    "message": "どちらにしろ自分で決めた事に変わりはない。"
  },
  {
    "name": "真弓",
    "message": "…私は主人を傷つけたくなかった。"
  },
  {
    "name": "たかふみ",
    "message": "その話はもういいや。"
  },
  {
    "name": "真弓",
    "message": "自分の幸せだって守りたかった。そう思う事のどこがいけないのか、教えて。"
  },
  {
    "name": "たかふみ",
    "message": "知らねぇよ、そんなの。"
  },
  {
    "name": "真弓",
    "message": "あの時、私がどうすれば良かったのか教えて。自尊心をボロボロにされてまで、我慢した私が馬鹿なのか教えてっ。"
  },
  {
    "name": "たかふみ",
    "message": "…何も泣く事はないだろ？"
  },
  {
    "name": "真弓",
    "message": "ひくっ…う…っ…は、早く教えてよっ。"
  },
  {
    "name": "たかふみ",
    "message": "…。"
  },
  {
    "message": "そう興奮するなってば"
  },
  {
    "message": "おっぱいが揺れてるぞ"
  },
  {
    "name": "たかふみ",
    "message": "そう興奮するなってば。"
  },
  {
    "name": "真弓",
    "message": "っ、だいたいあんたがいけないんじゃない。"
  },
  {
    "name": "たかふみ",
    "message": "いいから涙を拭けって…。"
  },
  {
    "name": "たかふみ",
    "message": "おっぱいが揺れてるぞ。"
  },
  {
    "name": "真弓",
    "message": "う…ひ、酷い…。"
  },
  {
    "name": "たかふみ",
    "message": "いいから涙を拭けって…。"
  },
  {
    "message": "俺のハンカチを貸してやる"
  },
  {
    "message": "自分のハンカチで拭かせる"
  },
  {
    "name": "たかふみ",
    "message": "…ほら。"
  },
  {
    "name": "真弓",
    "message": "ハ、ハンカチぐらい持ってるわよ。"
  },
  {
    "name": "たかふみ",
    "message": "誰のでもいいから、とにかく拭けって。"
  },
  {
    "name": "真弓",
    "message": "…。"
  },
  {
    "name": "たかふみ",
    "message": "ハンカチぐらい持ってるんだろ？"
  },
  {
    "name": "真弓",
    "message": "も、持ってるわよ。"
  },
  {
    "name": "たかふみ",
    "message": "じゃあ早く拭けって。"
  },
  {
    "name": "真弓",
    "message": "…。"
  },
  {
    "message": "女はハンカチを使わず手で涙を拭った。"
  },
  {
    "message": "でも拭った側から溢れてくるので、涙顔である事に全く変わりはない。"
  },
  {
    "message": "女の涙がけっこう被虐的だったせいだろうか。"
  },
  {
    "message": "いきなり意地の悪い考えが頭に浮かぶ。"
  },
  {
    "message": "こういう事にかけては天才だ。"
  },
  {
    "message": "俺は女の隙をつき。"
  },
  {
    "message": "逃げる余裕がない速さで耳元に口を近づけた。"
  },
  {
    "name": "真弓",
    "message": "な、何するのっ。"
  },
  {
    "name": "たかふみ",
    "message": "…。"
  },
  {
    "name": "真弓",
    "message": "…え？"
  },
  {
    "name": "たかふみ",
    "message": "だから…。"
  },
  {
    "message": "俺はごしょごしょ囁き続ける。"
  },
  {
    "message": "間近で見る首筋が色っぽい。"
  },
  {
    "name": "真弓",
    "message": "こ、この期に及んで、あんた、気でも狂ったの？"
  },
  {
    "name": "たかふみ",
    "message": "もし俺の願いを叶えてくれるなら、病気の事も一緒に教えてやるよ。"
  },
  {
    "name": "真弓",
    "message": "…最低。"
  },
  {
    "name": "たかふみ",
    "message": "くくっ、自分が馬鹿だったかどうか知りたい。そう言ったのは奥さんのほうじゃないか。"
  },
  {
    "name": "真弓",
    "message": "あんたが囁いた事と関係ないでしょ？"
  },
  {
    "name": "たかふみ",
    "message": "関係大ありだ。"
  },
  {
    "name": "真弓",
    "message": "…どうして？"
  },
  {
    "name": "たかふみ",
    "message": "拒絶すれば我慢した事が馬鹿だった事になる。受け入れたら、あんたの判断は正しかった事になる…違うかい？"
  },
  {
    "name": "真弓",
    "message": "…。"
  },
  {
    "name": "たかふみ",
    "message": "一昨日も今も判断の基準に変わりはないだろ？"
  },
  {
    "name": "真弓",
    "message": "…呼び出した私が間違ってたわ。"
  },
  {
    "name": "たかふみ",
    "message": "かもな。"
  },
  {
    "name": "真弓",
    "message": "…。"
  },
  {
    "name": "たかふみ",
    "message": "暑いから飲み物の一杯ぐらいご馳走してくれよ。"
  },
  {
    "name": "真弓",
    "message": "…変質者。"
  },
  {
    "name": "たかふみ",
    "message": "何とでも言ってくれ。俺のペニスに貫かれた事を今から後悔するか、旦那を守る為に必要だったと思うか…どっちだ？"
  },
  {
    "name": "真弓",
    "message": "っ、そんなの必要だったと思うしかないじゃない。無理にでもそう思う事ができなかったら、とっくにあんたを殺して私も死んでるわっ。"
  },
  {
    "name": "たかふみ",
    "message": "さすがだな、奥さん。"
  },
  {
    "name": "真弓",
    "message": "う…。"
  },
  {
    "name": "たかふみ",
    "message": "あんたは妻として亭主を守ったんだ。"
  },
  {
    "name": "真弓",
    "message": "でも、その考えを捨てない限り私はずっと…。"
  },
  {
    "name": "たかふみ",
    "message": "俺だってそのうち飽きる時が来る。そうなったら、あんたにゃ見向きもしないさ。"
  },
  {
    "name": "真弓",
    "message": "…本当に？"
  },
  {
    "name": "たかふみ",
    "message": "ああ、今までもそうだったし。俺の頭にはスイッチがあって、突然それが切り替わるんだ…もういいや、ってね。"
  },
  {
    "name": "真弓",
    "message": "…。"
  },
  {
    "name": "たかふみ",
    "message": "前にも言ったろ？"
  },
  {
    "name": "真弓",
    "message": "…覚えてるわ。"
  },
  {
    "name": "たかふみ",
    "message": "つまり、奥さんの我慢だって無駄じゃないんだよ。"
  },
  {
    "name": "真弓",
    "message": "…さっき囁いた事を叶えれば、病気の事も教えてくれる…の？"
  },
  {
    "name": "たかふみ",
    "message": "もちろん。"
  },
  {
    "name": "真弓",
    "message": "…。"
  },
  {
    "name": "たかふみ",
    "message": "ほら、どうするか歩きながら考えようぜ。ここでずっと立ち話をしてると、俺が虐めてるみたいに見えるから。"
  },
  {
    "name": "真弓",
    "message": "…離れて歩いて。"
  },
  {
    "name": "たかふみ",
    "message": "行き先はグリーンハイツ、だぜ。"
  },
  {
    "name": "真弓",
    "message": "…。"
  },
  {
    "message": "俺より数メートル前を歩く真弓。"
  },
  {
    "message": "後ろ姿もなかなか素敵だ。"
  },
  {
    "message": "何よりスタイルがいい。"
  },
  {
    "message": "長いスカートでもそれがはっきりわかる。"
  },
  {
    "message": "児童公園からグリーンハイツまでの、ちょうど中間地点に差し掛かった時。"
  },
  {
    "message": "急に真弓が立ち止まった。"
  },
  {
    "name": "たかふみ",
    "message": "追いついちゃうぞ。"
  },
  {
    "name": "真弓",
    "message": "…。"
  },
  {
    "name": "たかふみ",
    "message": "それともやっぱりやめた、とか？"
  },
  {
    "name": "真弓",
    "message": "約束して。"
  },
  {
    "name": "たかふみ",
    "message": "何を？"
  },
  {
    "name": "真弓",
    "message": "セックスはしないって。"
  },
  {
    "name": "たかふみ",
    "message": "いいとも。"
  },
  {
    "name": "真弓",
    "message": "…。"
  },
  {
    "message": "真弓はまだ疑わしそうな目を向けている。"
  },
  {
    "message": "しかし俺の表情は読み取れない。"
  },
  {
    "message": "結局、彼女は再び歩き始めるしかなかった。"
  },
  {
    "message": "それでいい。"
  },
  {
    "message": "グリーンハイツまで残り半分。"
  },
  {
    "message": "近づけば近づくほど俺を追い返せなくなる。"
  },
  {
    "message": "こいつはそういう女だ。"
  },
  {
    "message": "…。"
  },
  {
    "message": "……。"
  },
  {
    "message": "………。"
  },
  {
    "name": "たかふみ",
    "message": "着いちゃったな。"
  },
  {
    "name": "真弓",
    "message": "…。"
  },
  {
    "name": "たかふみ",
    "message": "どうする？"
  },
  {
    "name": "真弓",
    "message": "…ここで少し待ってて。"
  },
  {
    "name": "たかふみ",
    "message": "迷ってるならもういいや。"
  },
  {
    "name": "真弓",
    "message": "違う、そういう意味じゃない。"
  },
  {
    "name": "たかふみ",
    "message": "…。"
  },
  {
    "name": "真弓",
    "message": "…。"
  },
  {
    "name": "たかふみ",
    "message": "どれくらい待てばいいんだ？"
  },
  {
    "name": "真弓",
    "message": "５分くらいでいいわ。鍵、開けておくから…。"
  },
  {
    "name": "たかふみ",
    "message": "…。"
  },
  {
    "name": "たかふみ",
    "message": "…くくっ。"
  },
  {
    "message": "安心しな。"
  },
  {
    "message": "二人きりでのセックスなんか面白くないさ。"
  },
  {
    "message": "俺は単に。"
  },
  {
    "message": "オナニーの続きがしたいだけなんだよ…。"
  }
]