[
  {
    "message": "…二日後…"
  },
  {
    "message": "［千尋］：ふぅ…。"
  },
  {
    "message": "できた。"
  },
  {
    "message": "親子連れ受けしそうなポスターが３点。"
  },
  {
    "message": "カラフルな色合いに自分でも大満足。"
  },
  {
    "message": "「幸福が丘市役所、財務局自慢の味」"
  },
  {
    "message": "「美味しいヤキソバ２８０円（税込み）」"
  },
  {
    "message": "「ヤキソバを食べて町の緑を増やそう」"
  },
  {
    "message": "「売り上げは自治会の桜基金に寄付されます」"
  },
  {
    "message": "［千尋］：…。"
  },
  {
    "message": "私は預かった資料をもう一度確認。"
  },
  {
    "message": "大丈夫。"
  },
  {
    "message": "値段は間違ってない。"
  },
  {
    "message": "二人で考えたコピーも全て入れた。"
  },
  {
    "message": "言われたとおり「財務局自慢」の文字は大き目に。"
  },
  {
    "message": "これは翔ちゃんからのリクエスト。"
  },
  {
    "message": "何でも同じ役所内でもう一つ、ヤキソバの出店があるみたい。"
  },
  {
    "message": "どうしてそうなのかわからないけど。"
  },
  {
    "message": "たぶん翔ちゃんが張り切る理由も、それと無関係じゃないように思う。"
  },
  {
    "message": "［千尋］：はぁ…。"
  },
  {
    "message": "あっという間に過ぎた二日間。"
  },
  {
    "message": "昨日は画用紙とマーカーの買い出しに始まり。"
  },
  {
    "message": "帰りがけ銀行で釣り銭に使うお金を両替。"
  },
  {
    "message": "たったそれだけで半日が過ぎてしまい。"
  },
  {
    "message": "おかげで私はお料理教室まで休むハメに。"
  },
  {
    "message": "そして今日は朝からポスターの制作。"
  },
  {
    "message": "途中、翔ちゃんの浴衣にアイロンをかけ。"
  },
  {
    "message": "市役所の名前が入った腕章を、忘れないように袖へつけておく。"
  },
  {
    "message": "一応エプロンも袋の中へ。"
  },
  {
    "message": "「出店の人は浴衣のみ着用」"
  },
  {
    "message": "紙にはそう書いてあるけど、たぶん大丈夫と思ったから。"
  },
  {
    "message": "［千尋］：…。"
  },
  {
    "message": "時間は午後８時過ぎ。"
  },
  {
    "message": "翔ちゃんからの帰るコールは３０分くらい前。"
  },
  {
    "message": "このポスターを見たらどんな顔をするだろ？"
  },
  {
    "message": "私は久し振りに無邪気な笑顔。"
  },
  {
    "message": "ある意味、良かった。"
  },
  {
    "message": "イライラする気持ちを誤魔化せるほど忙しくて。"
  },
  {
    "message": "だって妙な焦燥感は膨らむばかり。"
  },
  {
    "message": "それでも作業に集中してる間は、何とか平常心を保つ事ができる。"
  },
  {
    "message": "まるで自分自身と戦ってるような気分。"
  },
  {
    "message": "どうしてこうなっちゃったのか、理由は相変わらず見つけられない。"
  },
  {
    "message": "ピンポーン。"
  },
  {
    "message": "［千尋］：は、はーい。"
  },
  {
    "message": "帰ってきた。"
  },
  {
    "message": "翔ちゃんだ。"
  },
  {
    "message": "［千尋］：っ、すぐ開けるから待って。"
  },
  {
    "message": "［優作］：こんばんわぁ、奥さん。"
  },
  {
    "message": "［千尋］：！！"
  },
  {
    "message": "［優作］：突然お邪魔してすみませんねぇ。"
  },
  {
    "message": "［千尋］：な、何をしに…。"
  },
  {
    "message": "そこまで言いかけ、言葉を飲み込んだ。"
  },
  {
    "message": "後ろに翔ちゃんの姿。"
  },
  {
    "message": "危うく墓穴を掘りかけた自分に、心臓がバクバクしちゃってる。"
  },
  {
    "message": "［千尋］：っ…いらっしゃいませ。"
  },
  {
    "message": "［優作］：プールの件では色々と世話になりました。"
  },
  {
    "message": "［千尋］：こ、こちらこそ。"
  },
  {
    "message": "［優作］：日焼けのほうは大丈夫でしたか？"
  },
  {
    "message": "［千尋］：っ、お陰様でなんとか…どうぞお上がり下さい。"
  },
  {
    "message": "［優作］：…それじゃ遠慮なく。"
  },
  {
    "message": "［翔太］：ただいまっ。"
  },
  {
    "message": "［千尋］：…お帰りなさい。"
  },
  {
    "message": "［翔太］：ちょっとだけ課長と明日の打ち合わせ…いい？"
  },
  {
    "message": "［千尋］：う、うん。"
  },
  {
    "message": "［千尋］：…。"
  },
  {
    "message": "やっぱり、だ。"
  },
  {
    "message": "一昨日の善人ブリはただの気まぐれ。"
  },
  {
    "message": "そう簡単に諦めてくれるわけがない。"
  },
  {
    "message": "緊張のせいか妙な焦燥感も急に消え失せ。"
  },
  {
    "message": "頭の中が悪魔の事でいっぱいになってる。"
  },
  {
    "message": "［千尋］：っ…。"
  },
  {
    "message": "擦れ違いざまお尻は触られなかった。"
  },
  {
    "message": "でも油断しちゃダメ。"
  },
  {
    "message": "何かしてきたら絶対に抵抗しよう。"
  },
  {
    "message": "もう足だって開いてあげない。"
  },
  {
    "message": "たとえ翔ちゃんが横にいようと、塵を見るような目で睨んでやる。"
  },
  {
    "message": "…。"
  },
  {
    "message": "［優作］：…って事だ。"
  },
  {
    "message": "［翔太］：わかりました。"
  },
  {
    "message": "［優作］：食材が届くのは午後３時。縁日が始まるまでに１時間ほどあるが、クーラーボックスだから心配はいらねぇ。"
  },
  {
    "message": "［翔太］：っ、何から何までありがとうございます。"
  },
  {
    "message": "［優作］：これが仕入れ先の電話番号だ。生麺は一応３００玉確保してある。"
  },
  {
    "message": "［優作］：もちろん最初に届くのは半分の１５０で、あとは様子を見ながら随時追加すりゃいい。場所は隣町だから１０分もありゃ着くだろ。"
  },
  {
    "message": "［翔太］：売り切れば１位は間違い無しですね。"
  },
  {
    "message": "［優作］：…だな。"
  },
  {
    "message": "［翔太］：釣り銭のほうは用意できてる？"
  },
  {
    "message": "［千尋］：…。"
  },
  {
    "message": "［翔太］：…千尋？"
  },
  {
    "message": "［千尋］：え？"
  },
  {
    "message": "［翔太］：銀行で両替はしてきた？"
  },
  {
    "message": "［千尋］：は、はい。"
  },
  {
    "message": "［翔太］：これで準備は完璧。"
  },
  {
    "message": "［優作］：おい…。"
  },
  {
    "message": "明日が楽しみだろ？"
  },
  {
    "message": "デキた奥さんがいるお前は幸せモンだな"
  },
  {
    "message": "［優作］：明日が楽しみだろ？"
  },
  {
    "message": "［翔太］：やるからには全力を尽くしますっ。"
  },
  {
    "message": "［優作］：…いい心がけだ。"
  },
  {
    "message": "［優作］：デキた奥さんがいるお前は幸せモンだな。"
  },
  {
    "message": "［翔太］：彼女がいなかったら、今の僕はありません。"
  },
  {
    "message": "［優作］：…ノロケるねぇ。"
  },
  {
    "message": "［千尋］：っ…。"
  },
  {
    "message": "［優作］：でもまだ準備完了じゃねぇと思うぜ。"
  },
  {
    "message": "［翔太］：心得てますからご心配なく。"
  },
  {
    "message": "［優作］：…さすが係長だ。"
  },
  {
    "message": "［翔太］：ヤキソバの味付けですよね？"
  },
  {
    "message": "［優作］：濃すぎず薄すぎず、万人受けを目指せ。"
  },
  {
    "message": "［翔太］：そっちのほうは任せて下さい。隣に強～い味方がいますから。"
  },
  {
    "message": "［千尋］：わ、私？"
  },
  {
    "message": "［優作］：なるほど…。"
  },
  {
    "message": "何も言わず奥さんを見る"
  },
  {
    "message": "奥さんは料理も上手だからな"
  },
  {
    "message": "じいいい…。"
  },
  {
    "message": "［千尋］：ぁ…。"
  },
  {
    "message": "［優作］：奥さんは料理も上手だからな。"
  },
  {
    "message": "［翔太］：やっぱり課長もそう思いますか？"
  },
  {
    "message": "［優作］：お前にゃ勿体ないくらいだよ。"
  },
  {
    "message": "［翔太］：そ、そこまで褒めて貰えるなんて光栄です。"
  },
  {
    "message": "［千尋］：ぅ…。"
  },
  {
    "message": "［翔太］：千尋、ヤキソバの麺は用意してあるよね？"
  },
  {
    "message": "［千尋］：め、麺を１０玉と…あとソースも、数種類…。"
  },
  {
    "message": "［翔太］：さすが僕の奥さん。頼りになるなぁ。"
  },
  {
    "message": "［優作］：…。"
  },
  {
    "message": "何も言わず奥さんを見る"
  },
  {
    "message": "仕事をさせたら旦那様より使えるかも"
  },
  {
    "message": "じいいい…。"
  },
  {
    "message": "［千尋］：ぅ…。"
  },
  {
    "message": "［翔太］：千尋って秘書向きかも。"
  },
  {
    "message": "［優作］：機転がきくだけじゃなく美人だし、だろ？"
  },
  {
    "message": "［優作］：仕事をさせたら旦那様より使えるかも。"
  },
  {
    "message": "［翔太］：じ、冗談キツいっすよ。"
  },
  {
    "message": "［優作］：デキるタイプの人間は、必ず先読みするモンだ。"
  },
  {
    "message": "［翔太］：っ、確かにそうですけど…。"
  },
  {
    "message": "［優作］：機転がきくだけじゃなく美人だし。"
  },
  {
    "message": "［翔太］：それには素直に同意しちゃいます。"
  },
  {
    "message": "［千尋］：っ…。"
  },
  {
    "message": "［優作］：本当に奥さんはモデル並の容姿だもんなぁ。"
  },
  {
    "message": "［翔太］：実はこのマンションにも、隠れファンがいるって噂で…。"
  },
  {
    "message": "［優作］：それには俺も素直に同意するぜ。"
  },
  {
    "message": "［千尋］：もうやめて下さい！！"
  },
  {
    "message": "［翔太］：お、おい。"
  },
  {
    "message": "［優作］：…。"
  },
  {
    "message": "［千尋］：…っ…。"
  },
  {
    "message": "椅子を揺らしながら立ち上がった私。"
  },
  {
    "message": "それくらい我慢できなかった。"
  },
  {
    "message": "その善人ぶった態度はなに？"
  },
  {
    "message": "あなたの褒め言葉なんか聞きたくもない。"
  },
  {
    "message": "思ってもいない事ばかり口にして。"
  },
  {
    "message": "これならまだ足を拡げられたほうがマシだ。"
  },
  {
    "message": "私はそのままキッチンへ。"
  },
  {
    "message": "自分でも驚くぐらい取り乱してる。"
  },
  {
    "message": "［千尋］：はぁ…っ…。"
  },
  {
    "message": "シンクの前で何回か深呼吸。"
  },
  {
    "message": "落ち着かないと。"
  },
  {
    "message": "なんでこんなに怒ってるんだろう。"
  },
  {
    "message": "冷静に考えればたわいもない会話。"
  },
  {
    "message": "上司を家へ招いた時によくある光景だ。"
  },
  {
    "message": "なのに私は声を荒げるほど興奮し。"
  },
  {
    "message": "思いっきり非礼な態度を取っちゃった。"
  },
  {
    "message": "潮が引くように冷めていく怒り。"
  },
  {
    "message": "それに準じて頬もだんだん青ざめてくる。"
  },
  {
    "message": "［千尋］：（ど、どうしよう…）"
  },
  {
    "message": "今さら後悔しても手遅れ。"
  },
  {
    "message": "バツが悪すぎて戻るに戻れない。"
  },
  {
    "message": "［優作］：…奥さん。"
  },
  {
    "message": "［千尋］：は、はい。"
  },
  {
    "message": "肩越しに聞こえてくる声。"
  },
  {
    "message": "恐くて後ろを振り向けなかった。"
  },
  {
    "message": "［優作］：気を悪くしたなら許して下さい。打ち合わせも無事に終わりましたし、あまり長居してもアレなので…。"
  },
  {
    "message": "［千尋］：え？"
  },
  {
    "message": "帰る？"
  },
  {
    "message": "本当に？"
  },
  {
    "message": "［優作］：じゃあな…頑張れよ。"
  },
  {
    "message": "［翔太］：あの、何だか…すみません…。"
  },
  {
    "message": "［優作］：…余計な事を言った俺がいけねぇんだ。"
  },
  {
    "message": "［千尋］：ぁ…。"
  },
  {
    "message": "私は夢でも見てる？"
  },
  {
    "message": "あの悪魔が謝るなんて。"
  },
  {
    "message": "玄関から聞こえてくる扉の開閉音。"
  },
  {
    "message": "これもきっと幻聴に違いない。"
  },
  {
    "message": "しつこさにかけては世界一の男だもの。"
  },
  {
    "message": "嫌がらせ一つせず素直に帰るモンか。"
  },
  {
    "message": "［翔太］：ど、どうしちゃったの？"
  },
  {
    "message": "［千尋］：…。"
  },
  {
    "message": "［千尋］：…帰った？"
  },
  {
    "message": "［翔太］：う、うん。"
  },
  {
    "message": "［千尋］：本当に？"
  },
  {
    "message": "［翔太］：さ、さっきから変だよ。いきなり怒り出すし、見送りもしないし…。"
  },
  {
    "message": "［千尋］：…。"
  },
  {
    "message": "やっぱりこれは夢だ。"
  },
  {
    "message": "［千尋］：あ…。"
  },
  {
    "message": "いけない。"
  },
  {
    "message": "鍵の事をすっかり忘れてた。"
  },
  {
    "message": "ポスト内になかった事は、悪魔だって知ってるはず。"
  },
  {
    "message": "それこそ帰り際に何か言えばいいのに。"
  },
  {
    "message": "返さないと。"
  },
  {
    "message": "もう持ってるのはイヤ。"
  },
  {
    "message": "［千尋］：か、課長さんに謝ってくるっ。"
  },
  {
    "message": "［翔太］：お、おい。"
  },
  {
    "message": "チェストからカスケットを鷲掴み。"
  },
  {
    "message": "私は呆然とする翔ちゃんを残し、慌てて悪魔の後を追いかけた。"
  },
  {
    "message": "かちゃっ…ばたんっ。"
  },
  {
    "message": "［千尋］：っ…。"
  },
  {
    "message": "エレベーターは２階のランプが灯ったばかり。"
  },
  {
    "message": "追いつける。"
  },
  {
    "message": "絶対に。"
  },
  {
    "message": "私はスカートの裾をなびかせ。"
  },
  {
    "message": "階段を一つ飛ばしに駆け下りる。"
  },
  {
    "message": "誰と擦れ違おうがかまわない。"
  },
  {
    "message": "胸の揺れだって気にするもんか。"
  },
  {
    "message": "［千尋］：はあっ…はあっ…はあっ…。"
  },
  {
    "message": "［優作］：あれぇ？"
  },
  {
    "message": "［千尋］：ぁ…っ…。"
  },
  {
    "message": "ほぼ同時。"
  },
  {
    "message": "私のほうが少し早かったかも。"
  },
  {
    "message": "［優作］：どうしたんですか、奥さん。"
  },
  {
    "message": "［千尋］：ど、どうしたって…。"
  },
  {
    "message": "私は息を整える間もなく、カスケットの蓋を開け。"
  },
  {
    "message": "預かってた鍵を悪魔に差し出した。"
  },
  {
    "message": "［優作］：…ポストの中で良かったのに。"
  },
  {
    "message": "［千尋］：っ、あとで難癖つけられるのはイヤですから。"
  },
  {
    "message": "［優作］：なるほど。"
  },
  {
    "message": "悪魔はさも納得したように頷き。"
  },
  {
    "message": "私の指に触れる事なく鍵を受け取る。"
  },
  {
    "message": "［優作］：わざわざありがとう。"
  },
  {
    "message": "［千尋］：そ、その気持ち悪い喋り方、やめてもらえませんか？"
  },
  {
    "message": "［優作］：じゃ、ヤキソバの味付けは宜しく。"
  },
  {
    "message": "［千尋］：っ、話を逸らさないで。"
  },
  {
    "message": "［優作］：それにしても転ばなくて良かった。"
  },
  {
    "message": "［千尋］：だ、だから私は…。"
  },
  {
    "message": "［優作］：早く戻らないと旦那さんが心配しますよ。"
  },
  {
    "message": "［千尋］：ぅ…っ…。"
  },
  {
    "message": "噛み合わない会話。"
  },
  {
    "message": "わざとらしい態度。"
  },
  {
    "message": "相手は何事もなかったように冷静。"
  },
  {
    "message": "そして私だけ何故か必死。"
  },
  {
    "message": "それがどうしても許せない。"
  },
  {
    "message": "［優作］：…そうだ。"
  },
  {
    "message": "［千尋］：！！"
  },
  {
    "message": "いきなり私は腕を掴まれる。"
  },
  {
    "message": "［千尋］：ち、ちょっと…。"
  },
  {
    "message": "［優作］：ここだと少しマズいんで。"
  },
  {
    "message": "［千尋］：っ…。"
  },
  {
    "message": "きた。"
  },
  {
    "message": "やっと本性を現した。"
  },
  {
    "message": "鍵の件で追いかけて来るのも想定内。"
  },
  {
    "message": "だからわざと忘れてるフリしてたんだ。"
  },
  {
    "message": "いかにもこの男が考えそうな事。"
  },
  {
    "message": "でも今度ばかりはいつものようにいかない。"
  },
  {
    "message": "変な事をしたら叫んでやる。"
  },
  {
    "message": "もうどこにも触らせるモンか。"
  },
  {
    "message": "引っ張る為に掴まれてる手首以外は。"
  },
  {
    "message": "［優作］：…ここなら大丈夫。"
  },
  {
    "message": "［千尋］：へ、変な事をしたら大声を出しますよ。"
  },
  {
    "message": "［優作］：一つ借りが残ってたのを、急に思い出しちゃって。"
  },
  {
    "message": "［千尋］：…え？"
  },
  {
    "message": "［優作］：頬を叩かせる約束。"
  },
  {
    "message": "［千尋］：ぁ…。"
  },
  {
    "message": "［優作］：思いっきりどうぞ。"
  },
  {
    "message": "［千尋］：そ、それで何もかも白紙に戻すつもりなんですね。"
  },
  {
    "message": "［優作］：気が済むだけ叩いて下さい。"
  },
  {
    "message": "［千尋］：っ…。"
  },
  {
    "message": "やっとわかった。"
  },
  {
    "message": "不可解なイライラの理由。"
  },
  {
    "message": "全てはこの男の無責任さが原因なんだ。"
  },
  {
    "message": "私を滅茶苦茶にしておいて。"
  },
  {
    "message": "自分だけ勝手に過去へ巻き戻ったそぶり。"
  },
  {
    "message": "奈落へ突き落としたのはあなたのクセに。"
  },
  {
    "message": "元に戻して。"
  },
  {
    "message": "あなたと関わる前の私に戻して。"
  },
  {
    "message": "［千尋］：た、叩きません。"
  },
  {
    "message": "［優作］：きっとスッキリしますよ。"
  },
  {
    "message": "［千尋］：っ、スッキリなんかしない。"
  },
  {
    "message": "［優作］：試してみたらどうでしょう。"
  },
  {
    "message": "［千尋］：だ、だからその言葉遣いはやめて！！"
  },
  {
    "message": "何かが身体の中で爆発した。"
  },
  {
    "message": "信じられないくらい気持ちが動揺し。"
  },
  {
    "message": "滝のように涙まで溢れてくる。"
  },
  {
    "message": "取り乱し方がさっきの比じゃない。"
  },
  {
    "message": "とうとう私はここが外である事も忘れ。"
  },
  {
    "message": "ワーワー声を上げ泣き出してしまう。"
  },
  {
    "message": "誰かが来る事も恐れず。"
  },
  {
    "message": "窓の明かりが灯る事も気にせず。"
  },
  {
    "message": "ただただ子供みたいに泣きじゃくる私。"
  },
  {
    "message": "そして気が付けば独りぼっち。"
  },
  {
    "message": "いつの間にか悪魔がいなくなってた。"
  },
  {
    "message": "［千尋］：ぇ…ぇ…？"
  },
  {
    "message": "また放置。"
  },
  {
    "message": "酷いよ。"
  },
  {
    "message": "全てあなたのせいなのに。"
  },
  {
    "message": "知らんぷりで帰るなんて。"
  },
  {
    "message": "もちろん慰めて欲しいとは思ってない。"
  },
  {
    "message": "私はただ…。"
  },
  {
    "message": "［千尋］：…。"
  },
  {
    "message": "…ただ？"
  },
  {
    "message": "ただ、何、なの？"
  },
  {
    "message": "いったい何を望んでるわけ？"
  },
  {
    "message": "いないほうがホッとできるはず。"
  },
  {
    "message": "なのに私はプリプリ怒ってる。"
  },
  {
    "message": "辻褄が全く合ってない。"
  },
  {
    "message": "自分でも呆れるくらいに。"
  },
  {
    "message": "［千尋］：ぐすっ…。"
  },
  {
    "message": "もういい。"
  },
  {
    "message": "あんな男の事なんか二度と考えるものか。"
  },
  {
    "message": "［千尋］：はぁ…。"
  },
  {
    "message": "追いかけた時と正反対で、足が鉛のように重かった。"
  },
  {
    "message": "私は入り口の前で立ち止まり。"
  },
  {
    "message": "腫れぼったくなった瞼を、指先でぎゅっと押さえる。"
  },
  {
    "message": "何とか泣いた痕跡を消したい。"
  },
  {
    "message": "私が考えられるのは、もう目先の事だけだ。"
  },
  {
    "message": "［翔太］：ち、千尋っ。"
  },
  {
    "message": "［千尋］：！？"
  },
  {
    "message": "［千尋］：ぁ…。"
  },
  {
    "message": "［翔太］：っ…。"
  },
  {
    "message": "［千尋］：ど、どうしたの？"
  },
  {
    "message": "［翔太］：それはこっちのセリフでしょ。"
  },
  {
    "message": "［千尋］：…。"
  },
  {
    "message": "声をかけられたのは後ろから。"
  },
  {
    "message": "つまり道路の方向から来た事になる。"
  },
  {
    "message": "［千尋］：も、もしかして…私を探してた？"
  },
  {
    "message": "［翔太］：遅いから心配したよぉ。"
  },
  {
    "message": "［千尋］：ごめん…なさい…。"
  },
  {
    "message": "私は視線だけじゃなく顔まで俯かせ。"
  },
  {
    "message": "必死になって充血した目を誤魔化してた。"
  },
  {
    "message": "［翔太］：何かあったのかと思っちゃった。"
  },
  {
    "message": "［千尋］：あ、謝りついでに駅まで送ってたから…。"
  },
  {
    "message": "［翔太］：…そっか。"
  },
  {
    "message": "［千尋］：ぅ…っ…。"
  },
  {
    "message": "嘘つき。"
  },
  {
    "message": "［翔太］：逆に課長のほうが驚いてたでしょ？"
  },
  {
    "message": "［千尋］：…え？"
  },
  {
    "message": "［翔太］：千尋が追いかけて来た事。"
  },
  {
    "message": "［千尋］：う、うん…まあ…。"
  },
  {
    "message": "［翔太］：許してもらえた？"
  },
  {
    "message": "［千尋］：ぁ…気にしないで下さいって。"
  },
  {
    "message": "［翔太］：よ、良かったぁ。"
  },
  {
    "message": "［千尋］：っ…っ…。"
  },
  {
    "message": "もうだめだ。"
  },
  {
    "message": "こんなの耐えられない。"
  },
  {
    "message": "私が側にいると翔ちゃんの足を引っ張る。"
  },
  {
    "message": "再び目から滝のような涙。"
  },
  {
    "message": "激しい嗚咽に肩までヒクヒク震えてきた。"
  },
  {
    "message": "［翔太］：ど、どうしたの？"
  },
  {
    "message": "［千尋］：ひくっ…。"
  },
  {
    "message": "私は翔ちゃんにしがみつく。"
  },
  {
    "message": "［翔太］：っ、何か課長に言われたとか？"
  },
  {
    "message": "［千尋］：ぐすっ…違うっ…。"
  },
  {
    "message": "［翔太］：じ、じゃあ…。"
  },
  {
    "message": "［千尋］：こ、ここに住みたくない…私、田舎に帰りたいぃ…っ。"
  },
  {
    "message": "［翔太］：え～っ。"
  },
  {
    "message": "［千尋］：っ…ひぐっ…ぐすっ…。"
  },
  {
    "message": "当然の如く理由を訊く彼。"
  },
  {
    "message": "でも私は何一つ答えられなかった。"
  },
  {
    "message": "泣いてたからじゃない。"
  },
  {
    "message": "自分のした事を彼に言えなかっただけ。"
  },
  {
    "message": "結果が同じなら想い出は綺麗なままに。"
  },
  {
    "message": "ただのワガママ女なら、まだ気持ちは救われる。"
  },
  {
    "message": "［千尋］：ひっ…ぐすっ…。"
  },
  {
    "message": "私は唇をぎゅっと噛んだ。"
  },
  {
    "message": "翔ちゃんの匂い。"
  },
  {
    "message": "たぶんこれが最後。"
  },
  {
    "message": "頬を伝う雫が掌を濡らし。"
  },
  {
    "message": "まるで指輪を緩めるよう、涙が隙間へ浸透してくる…。"
  },
  {
    "message": "…。"
  },
  {
    "message": "……。"
  },
  {
    "message": "………。"
  },
  {
    "message": "また泣きそう。"
  },
  {
    "message": "翔ちゃんに申し分けなくて。"
  },
  {
    "message": "［翔太］：じゃ、部屋に戻って始めよっか。"
  },
  {
    "message": "［千尋］：な、何を？"
  },
  {
    "message": "［翔太］：ヤキソバ作りの練習。"
  },
  {
    "message": "［千尋］：あ…。"
  },
  {
    "message": "いけない。"
  },
  {
    "message": "泣いてる場合じゃなかったんだ。"
  },
  {
    "message": "［千尋］：じ、時間は…。"
  },
  {
    "message": "［翔太］：今は１０時ぴったり。"
  },
  {
    "message": "［千尋］：っ、急がないと寝るのが遅くなっちゃう。"
  },
  {
    "message": "［優作］：縁日の始まりは夕方だから平気だって。"
  },
  {
    "message": "そう言いながらも私に促され。"
  },
  {
    "message": "二人揃って小走りにエントランスへ。"
  },
  {
    "message": "こういう時でさえ彼は一人で先に行かず。"
  },
  {
    "message": "ちゃんと私の歩調に合わせてくれる。"
  },
  {
    "message": "優しい翔ちゃん。"
  },
  {
    "message": "絶対に私の事を放置したりしない。"
  },
  {
    "message": "あの悪魔とは大違いだ。"
  },
  {
    "message": "［千尋］：…。"
  },
  {
    "message": "でも…。"
  },
  {
    "message": "私ってここまで気を遣われるほどの女？"
  },
  {
    "message": "本当なら先に彼がエレベーターへ乗り込み。"
  },
  {
    "message": "冷たい視線でこっちを振り返りながら。"
  },
  {
    "message": "「ダメ女は階段を使え」"
  },
  {
    "message": "そう言われるぐらいが相応しいかも。"
  },
  {
    "message": "相手が翔ちゃんなら納得する。"
  },
  {
    "message": "私は一人寂しく階段を登り。"
  },
  {
    "message": "彼が待つ３階のエレベーター前へ。"
  },
  {
    "message": "でもそこには誰もいない。"
  },
  {
    "message": "私の事なんか待ってない。"
  },
  {
    "message": "ガッカリしながら玄関のチャイムを押す私。"
  },
  {
    "message": "だけど返事は無し。"
  },
  {
    "message": "たぶん上るのが遅かった罰。"
  },
  {
    "message": "きっと翔ちゃんの機嫌が直るまで。"
  },
  {
    "message": "私は外で立ち尽くしてるしかないんだ…。"
  },
  {
    "message": "…。"
  },
  {
    "message": "……。"
  },
  {
    "message": "………。"
  }
]